DataValidityCheck/__init__.py
DataValidityCheck/validate_info_data.py
datavaliditycheck-0.0.4.dist-info/METADATA
datavaliditycheck-0.0.4.dist-info/WHEEL
datavaliditycheck-0.0.4.dist-info/RECORD
