Metadata-Version: 2.3
Name: DataValidityCheck
Version: 0.0.4
Summary: A Python package for validating various types of data.
License: MIT
Author: Olajide Oluwafemi
Author-email: olajiderichard44@gmail.com
Classifier: License :: OSI Approved :: MIT License
Classifier: Programming Language :: Python :: 2
Classifier: Programming Language :: Python :: 2.7
Classifier: Programming Language :: Python :: 3
Classifier: Programming Language :: Python :: 3.4
Classifier: Programming Language :: Python :: 3.5
Classifier: Programming Language :: Python :: 3.6
Classifier: Programming Language :: Python :: 3.7
Classifier: Programming Language :: Python :: 3.8
Classifier: Programming Language :: Python :: 3.9
Classifier: Programming Language :: Python :: 3.10
Classifier: Programming Language :: Python :: 3.11
Classifier: Programming Language :: Python :: 3.12
Classifier: Programming Language :: Python :: 3.13
Project-URL: Homepage, https://github.com/Data-Epic/Data-Validator-Oluwafemi-Olajide.git
Project-URL: Repository, https://github.com/Data-Epic/Data-Validator-Oluwafemi-Olajide.git
